calculator_program/__init__.py
calculator_program/calculator.py
PROJECT_PYPI-0.0.1.dist-info/METADATA
PROJECT_PYPI-0.0.1.dist-info/WHEEL
PROJECT_PYPI-0.0.1.dist-info/license.txt
PROJECT_PYPI-0.0.1.dist-info/top_level.txt
PROJECT_PYPI-0.0.1.dist-info/RECORD
