Metadata-Version: 2.1
Name: PROJECT-PYPI
Version: 0.0.1
Summary: My first Python package
Author: varalakshmi
Author-email: <varalakshmi6051998@gmail.com>
Keywords: python,first package
Classifier: Development Status :: 3 - Alpha
Classifier: Intended Audience :: Education
Classifier: Programming Language :: Python :: 2
Classifier: Programming Language :: Python :: 3
Classifier: Operating System :: MacOS :: MacOS X
Classifier: Operating System :: Microsoft :: Windows
License-File: license.txt
